README.rst
setup.py
spinning/__init__.py
spinning/mains.py
spinning.egg-info/PKG-INFO
spinning.egg-info/SOURCES.txt
spinning.egg-info/dependency_links.txt
spinning.egg-info/entry_points.txt
spinning.egg-info/requires.txt
spinning.egg-info/top_level.txt