Metadata-Version: 1.1
Name: spinning
Version: 0.1.0
Summary: spinning animation
Home-page: https://github.com/harshasrinivas/spinning/
Author: Harsha Srinivas
Author-email: 95harsha95@gmail.com
License: UNKNOWN
Keywords: python,animation,beautify
Platform: UNKNOWN
Classifier: Operating System :: POSIX
Classifier: Environment :: Console
Classifier: Programming Language :: Python
Classifier: Programming Language :: Python :: 2
Classifier: Programming Language :: Python :: 3
Classifier: Programming Language :: Python :: 3.5
Classifier: Topic :: Utilities
Classifier: Topic :: Software Development :: Libraries :: Python Modules
